ndx_dbs/__init__.py
ndx_dbs/spec/ndx-dbs.extensions.yaml
ndx_dbs/spec/ndx-dbs.namespace.yaml
ndx_dbs-0.1.0.dist-info/LICENSE.txt
ndx_dbs-0.1.0.dist-info/METADATA
ndx_dbs-0.1.0.dist-info/WHEEL
ndx_dbs-0.1.0.dist-info/top_level.txt
ndx_dbs-0.1.0.dist-info/RECORD
