Metadata-Version: 2.1
Name: ndx-dbs
Version: 0.1.0
Summary: This extension is developed to extend NWB data standards to incorporate DBS(DeepBrainStimulation) experiments.
Home-page: 
Author: Hamidreza Alimohammadi ([AT]DefenseCircuitsLab)
Author-email: "Hamidreza Alimohammadi ([AT]DefenseCircuitsLab)" <alimohammadi.hamidreza@gmail.com>
License: BSD-3
Keywords: NeurodataWithoutBorders,NWB,nwb-extension,ndx-extension
Classifier: Intended Audience :: Developers
Classifier: Intended Audience :: Science/Research
Classifier: License :: OSI Approved :: BSD License
License-File: LICENSE.txt
Requires-Dist: pynwb >=2.5.0
Requires-Dist: hdmf >=3.10.0
